[{"name":"group1","members":[],"dateModified":1368656310976,"dateSynchronized":null,"id":"group1"},{"name":"group2","members":["user1","user2","user3"],"dateModified":1368656310976,"dateSynchronized":null,"id":"group2"},{"name":"groupX","members":["userY","userZ"],"dateModified":1368656310976,"dateSynchronized":null,"id":"groupX"},{"name":"asda","members":[],"dateModified":1368656310976,"dateSynchronized":null,"id":"asda"},{"name":"bbbb","members":[],"dateModified":1368656310976,"dateSynchronized":null,"id":"bbbb"},{"name":"ccc","members":[],"dateModified":1368656575564,"dateSynchronized":null,"id":"ccc"}]